abc_sphinx/tests/test_functional.py
abc_sphinx/tests/test_units.py
abc_sphinx_extensions-0.1.dist-info/LICENSE
abc_sphinx_extensions-0.1.dist-info/METADATA
abc_sphinx_extensions-0.1.dist-info/WHEEL
abc_sphinx_extensions-0.1.dist-info/top_level.txt
abc_sphinx_extensions-0.1.dist-info/RECORD
