Metadata-Version: 2.1
Name: abc-sphinx-extensions
Version: 0.1
Summary: Sphinx extensions for creating tunebooks with abcfiles
Home-page: UNKNOWN
Author: Tim Pillinger
License: GPL
Platform: UNKNOWN
Classifier: Programming Language :: Python :: 3
Classifier: Operating System :: OS Independent
Requires-Dist: sphinx (>=2.1)
Requires-Dist: flake8
Requires-Dist: pytest
